{
  "adult": false, 
  "also_known_as": [], 
  "biography": "From Wikipedia, the free encyclopedia.\n\nMarissa Tait (b. May 27, 1979 in San Diego, CA) is an American actress.\n\nDescription above from the Wikipedia article Marissa Tait, licensed under CC-BY-SA, full list of contributors on Wikipedia.", 
  "birthday": "1979-05-27", 
  "deathday": "", 
  "homepage": "", 
  "id": 35456, 
  "imdb_id": "nm0846903", 
  "name": "Marissa Tait", 
  "place_of_birth": "San Diego, California, USA", 
  "popularity": 0.002442, 
  "profile_path": "/xDvxLVDgeSKrkQxK2x27umLbid4.jpg"
}